README.rst
example.py
lxmlmate.py
setup.py
lxml_mate.egg-info/PKG-INFO
lxml_mate.egg-info/SOURCES.txt
lxml_mate.egg-info/dependency_links.txt
lxml_mate.egg-info/top_level.txt