Metadata-Version: 1.1
Name: lxml-mate
Version: 0.5.3
Summary: The simplest Object-XML mapper for Python. Mate for lxml.
Home-page: https://github.com/david-shu/lxml-mate
Author: David Shu
Author-email: david.shu@126.com
License: MIT
Keywords: xml lxml
Platform: UNKNOWN
Classifier: Programming Language :: Python
Classifier: Programming Language :: Python :: 2.7
Classifier: Programming Language :: Python :: 3
Classifier: License :: OSI Approved
Classifier: License :: OSI Approved :: MIT License
Classifier: Development Status :: 5 - Production/Stable
Classifier: Intended Audience :: Developers
Classifier: Topic :: Text Processing
Classifier: Topic :: Text Processing :: Markup
Classifier: Topic :: Text Processing :: Markup :: XML
Requires: lxml
